{
  "uid": "39e6200133bb4755a737fc97cbe188e6",
  "name": "test",
  "imageName": "7442ff603d1042d995a64bbcfeb1b1fc.png",
  "labelData": [
    {
      "index": 0,
      "active": 0,
      "type": "anchor",
      "value": "限乘当日当次车",
      "points": [
        {
          "x": 308,
          "y": 558
        },
        {
          "x": 688,
          "y": 558
        },
        {
          "x": 688,
          "y": 638
        },
        {
          "x": 308,
          "y": 638
        }
      ]
    },
    {
      "index": 1,
      "active": 0,
      "type": "anchor",
      "value": "中国铁路祝您旅途愉快",
      "points": [
        {
          "x": 515,
          "y": 825
        },
        {
          "x": 998,
          "y": 825
        },
        {
          "x": 998,
          "y": 883
        },
        {
          "x": 515,
          "y": 883
        }
      ]
    },
    {
      "index": 2,
      "active": 0,
      "type": "rectangle",
      "value": "南昌站",
      "field": "start",
      "points": [
        {
          "x": 340,
          "y": 283
        },
        {
          "x": 695,
          "y": 283
        },
        {
          "x": 695,
          "y": 378
        },
        {
          "x": 340,
          "y": 378
        }
      ]
    },
    {
      "index": 3,
      "active": 0,
      "type": "rectangle",
      "value": "D6262",
      "field": "ticket",
      "points": [
        {
          "x": 773,
          "y": 285
        },
        {
          "x": 1013,
          "y": 285
        },
        {
          "x": 1013,
          "y": 375
        },
        {
          "x": 773,
          "y": 375
        }
      ]
    },
    {
      "index": 4,
      "active": 0,
      "type": "rectangle",
      "value": "九江站",
      "field": "end",
      "points": [
        {
          "x": 1073,
          "y": 280
        },
        {
          "x": 1423,
          "y": 280
        },
        {
          "x": 1423,
          "y": 373
        },
        {
          "x": 1073,
          "y": 373
        }
      ]
    }
  ]
}